README
setup.py
django_gishelper.egg-info/PKG-INFO
django_gishelper.egg-info/SOURCES.txt
django_gishelper.egg-info/dependency_links.txt
django_gishelper.egg-info/top_level.txt
gishelper/__init__.py
gishelper/models.py
gishelper/router.py
gishelper/utils.py
gishelper/management/__init__.py
gishelper/management/commands/__init__.py
gishelper/management/commands/inspectgeo.py
gishelper/management/commands/loadgeo.py