Metadata-Version: 1.0
Name: django-gishelper
Version: 0.0.2
Summary: Geodjango helper commands.
